{
  "instance": "R204",
  "vehicles": 8,
  "total_distance": 991.0,
  "capacity": 200,
  "horizon": 1000.0,
  "feasible": true,
  "routes": [
    [
      54,
      27,
      13,
      55,
      5,
      56,
      26,
      25,
      30,
      81,
      69,
      78,
      29
    ],
    [
      41,
      22,
      73,
      57,
      40,
      68,
      24,
      76,
      75,
      74,
      59
    ],
    [
      70,
      32,
      89,
      63,
      11,
      64,
      91,
      33,
      21,
      52,
      10,
      82,
      34,
      51
    ],
    [
      96,
      98,
      93,
      99,
      38,
      101,
      92,
      17,
      62,
      86,
      94,
      60,
      7
    ],
    [
      95,
      97,
      100,
      6,
      85,
      18,
      46,
      84,
      61,
      90
    ],
    [
      3,
      23,
      42,
      58,
      16,
      44,
      15,
      45,
      87,
      39,
      43,
      88,
      14
    ],
    [
      53,
      8,
      49,
      20,
      12,
      65,
      50,
      37,
      48,
      47,
      9,
      83,
      19
    ],
    [
      77,
      4,
      80,
      79,
      35,
      36,
      72,
      66,
      67,
      31,
      71,
      2,
      28
    ]
  ]
}