{
  "instance": "RC108",
  "vehicles": 11,
  "total_distance": 1424.0,
  "capacity": 200,
  "horizon": 240.0,
  "feasible": true,
  "routes": [
    [
      70,
      99,
      91,
      62,
      82,
      97,
      95,
      94,
      55,
      69
    ],
    [
      73,
      72,
      35,
      51,
      63,
      96,
      93,
      81
    ],
    [
      71,
      3,
      7,
      9,
      47,
      5,
      46,
      6,
      4,
      2,
      101
    ],
    [
      68,
      32,
      30,
      28,
      27,
      29,
      31,
      33,
      34
    ],
    [
      42,
      43,
      45,
      44,
      41,
      39,
      38,
      36,
      37,
      40
    ],
    [
      65,
      23,
      20,
      19,
      49,
      50,
      21,
      84,
      67
    ],
    [
      66,
      58,
      75,
      78,
      26,
      24,
      22,
      25
    ],
    [
      13,
      12,
      14,
      10,
      11,
      16,
      17,
      18,
      48,
      15
    ],
    [
      52,
      77,
      90,
      64,
      86,
      85,
      57,
      92
    ],
    [
      83,
      100,
      53,
      87,
      88,
      60,
      98,
      76,
      59
    ],
    [
      89,
      8,
      80,
      74,
      54,
      79,
      61,
      56
    ]
  ]
}